microform/__init__.py
microform/article_format.py
microform/mercury.py
microform/microform.py
microform-0.1.14.dist-info/DESCRIPTION.rst
microform-0.1.14.dist-info/METADATA
microform-0.1.14.dist-info/RECORD
microform-0.1.14.dist-info/WHEEL
microform-0.1.14.dist-info/entry_points.txt
microform-0.1.14.dist-info/metadata.json
microform-0.1.14.dist-info/top_level.txt
