Metadata-Version: 2.0
Name: microform
Version: 0.1.14
Summary: Command-line utility for reading articles in the terminal
Home-page: https://github.com/mosegontar/microform
Author: Alexander Gontar
Author-email: mosegontar@gmail.com
License: MIT
Platform: UNKNOWN
Requires-Dist: requests
Requires-Dist: requests-cache
Requires-Dist: tomd
